source_merge/__init__.py
source_merge/manifest.yaml
source_merge/run.py
source_merge/schemas/account_details.json
source_merge/schemas/activities.json
source_merge/schemas/applications.json
source_merge/schemas/attachments.json
source_merge/schemas/candidates.json
source_merge/schemas/departments.json
source_merge/schemas/eeocs.json
source_merge/schemas/interviews.json
source_merge/schemas/job_interview_stages.json
source_merge/schemas/jobs.json
source_merge/schemas/offers.json
source_merge/schemas/offices.json
source_merge/schemas/sync_status.json
source_merge/schemas/users.json
source_merge/source.py
source_merge/spec.yaml
airbyte_source_merge-0.1.15.dist-info/METADATA
airbyte_source_merge-0.1.15.dist-info/WHEEL
airbyte_source_merge-0.1.15.dist-info/entry_points.txt
airbyte_source_merge-0.1.15.dist-info/RECORD
